README.rst
setup.py
testsuite/__init__.py
testsuite/prettyprint/__init__.py
testsuite/prettyprint/traceback/__init__.py
testsuite/prettyprint/traceback/reporter.py
testsuite_prettyprint_traceback.egg-info/PKG-INFO
testsuite_prettyprint_traceback.egg-info/SOURCES.txt
testsuite_prettyprint_traceback.egg-info/dependency_links.txt
testsuite_prettyprint_traceback.egg-info/namespace_packages.txt
testsuite_prettyprint_traceback.egg-info/requires.txt
testsuite_prettyprint_traceback.egg-info/top_level.txt