Metadata-Version: 1.0
Name: testsuite-prettyprint-traceback
Version: 0.1.0-alpha
Summary: testsuite-prettyprint-traceback is a nose2 plugin that prettyprints traceback on failures and errors.
Home-page: UNKNOWN
Author: Omer Katz
Author-email: omer.drow@gmail.com
License: BSD3
Platform: UNKNOWN
